divider/__init__.py
divider/divide.py
divider-0.1.dist-info/METADATA
divider-0.1.dist-info/WHEEL
divider-0.1.dist-info/top_level.txt
divider-0.1.dist-info/RECORD
