Metadata-Version: 2.4
Name: divider
Version: 0.1
Summary: کتابخانه‌ای ساده برای تقسیم عدد بر ۲
Home-page: https://github.com/yourusername/divider
Author: Your Name
Author-email: your.email@example.com
Classifier: Programming Language :: Python :: 3
Classifier: License :: OSI Approved :: MIT License
Requires-Python: >=3.6
Dynamic: author
Dynamic: author-email
Dynamic: classifier
Dynamic: description
Dynamic: description-content-type
Dynamic: home-page
Dynamic: requires-python
Dynamic: summary
